SingleLog/SingleLog.py
SingleLog/__init__.py
SingleLog/log.py
SingleLog/utils.py
SingleLog-2.1.1.dist-info/LICENSE
SingleLog-2.1.1.dist-info/METADATA
SingleLog-2.1.1.dist-info/WHEEL
SingleLog-2.1.1.dist-info/top_level.txt
SingleLog-2.1.1.dist-info/RECORD
