Metadata-Version: 2.1
Name: SingleLog
Version: 2.1.1
Summary: # SingleLog
Home-page: https://github.com/PttCodingMan/SingleLog
Author: CodingMan
Author-email: pttcodingman@gmail.com
Keywords: log,logger,library
Classifier: Development Status :: 5 - Production/Stable
Classifier: Operating System :: OS Independent
Classifier: Topic :: Software Development :: Libraries :: Python Modules
Classifier: License :: OSI Approved :: MIT License
Classifier: Programming Language :: Python :: 3.8
Classifier: Programming Language :: Python :: 3.9
Classifier: Programming Language :: Python :: 3.10
Classifier: Programming Language :: Python :: 3.11
Requires-Python: >=3.8
License-File: LICENSE
Requires-Dist: AutoStrEnum
Requires-Dist: colorama
